kanga/__init__.py
kanga/chains/__init__.py
kanga/chains/chain_array.py
kanga/chains/chain_arrays.py
kanga/emulators/__init__.py
kanga/emulators/approx_ar_cov_sum.py
kanga/emulators/fit_ar.py
kanga/emulators/optimal_ar_batch_size.py
kanga/linalg/__init__.py
kanga/linalg/is_pos_def.py
kanga/linalg/nearest_pd.py
kanga/plots/__init__.py
kanga/plots/acf.py
kanga/plots/cmaps.py
kanga/plots/cor_heatmap.py
kanga/plots/hist.py
kanga/plots/hist2d.py
kanga/plots/running_mean.py
kanga/plots/trace.py
kanga/stats/__init__.py
kanga/stats/batch_mean.py
kanga/stats/batch_var.py
kanga/stats/bm_cov.py
kanga/stats/bm_mc_cov.py
kanga/stats/cor.py
kanga/stats/cor_from_cov.py
kanga/stats/inse_mc_cov.py
kanga/stats/mc_cor.py
kanga/stats/mc_cov.py
kanga/stats/mc_se.py
kanga/stats/mc_se_from_cov.py
kanga/stats/mean_array_summary.py
kanga/stats/mean_cor.py
kanga/stats/multi_ess.py
kanga/stats/multi_rhat.py
kanga/stats/running_mean.py
kanga-0.0.20.dist-info/LICENSE.txt
kanga-0.0.20.dist-info/METADATA
kanga-0.0.20.dist-info/WHEEL
kanga-0.0.20.dist-info/top_level.txt
kanga-0.0.20.dist-info/RECORD
